pypactum/__init__.py
pypactum/_assertion_kind.py
pypactum/_capture_set.py
pypactum/_contract_assertion_label.py
pypactum/_contract_violation.py
pypactum/_contract_violation_exception.py
pypactum/_contract_violation_handler.py
pypactum/_evaluation_semantic.py
pypactum/_invariant.py
pypactum/_post.py
pypactum/_pre.py
pypactum/_predicate.py
pypactum/handlers.py
pypactum/labels.py
pypactum/py.typed
pypactum/_utils/_assert_contract.py
pypactum/_utils/_effective_semantic.py
pypactum/_utils/_map_function_arguments.py
pypactum/_utils/_parent_frame.py
pypactum/_utils/_resolve_bindings.py
pypactum-0.3.4.dist-info/LICENSE
pypactum-0.3.4.dist-info/METADATA
pypactum-0.3.4.dist-info/WHEEL
pypactum-0.3.4.dist-info/top_level.txt
pypactum-0.3.4.dist-info/RECORD
