Metadata-Version: 2.2
Name: pypactum
Version: 0.3.4
Summary: Checkable contracts for python
Author: Jan Möller
License: MIT License
Project-URL: Homepage, https://github.com/jan-moeller/pactum
Project-URL: Documentation, https://github.com/jan-moeller/pactum/blob/main/README.md
Project-URL: Repository, https://github.com/jan-moeller/pactum.git
Project-URL: Issues, https://github.com/jan-moeller/pactum/issues
Keywords: contract,assertion,correctness,documentation,precondition,postcondition,function
Classifier: Development Status :: 3 - Alpha
Classifier: Intended Audience :: Developers
Classifier: Topic :: Documentation
Classifier: Topic :: Software Development
Classifier: Topic :: Software Development :: Libraries
Classifier: Topic :: Utilities
Classifier: Programming Language :: Python :: 3
Classifier: Programming Language :: Python :: 3.13
Requires-Python: >=3.13
License-File: LICENSE
Provides-Extra: tests
Requires-Dist: pytest; extra == "tests"
